{
    "id": "api.framework.read",
    "ver": "1.0",
    "ts": "2022-04-26T06:07:50.473Z",
    "params": {
      "resmsgid": "33c72b90-c527-11ec-8b57-c5cb801c89d2",
      "msgid": "dfc9921b-96cc-abd5-1baa-ef9845865789",
      "status": "successful",
      "err": null,
      "errmsg": null
    },
    "responseCode": "OK",
    "result": {
      "framework": {
        "identifier": "ekstep_ncert_k-12",
        "code": "ekstep_ncert_k-12",
        "name": "Centre",
        "description": "Centre",
        "categories": [
          {
            "identifier": "ekstep_ncert_k-12_board",
            "code": "board",
            "terms": [
              {
                "associations": [
                  {
                    "identifier": "ekstep_ncert_k-12_subject_science",
                    "code": "science",
                    "translations": null,
                    "name": "Science",
                    "description": "Science",
                    "index": 0,
                    "category": "subject",
                    "status": "Live"
                  },
                  {
                    "identifier": "ekstep_ncert_k-12_subject_geography",
                    "code": "geography",
                    "translations": null,
                    "name": "Geography",
                    "description": "Geography",
                    "index": 0,
                    "category": "subject",
                    "status": "Live"
                  },
                  {
                    "identifier": "ekstep_ncert_k-12_gradelevel_class1",
                    "code": "class1",
                    "translations": null,
                    "name": "Class 1",
                    "description": "Class 1",
                    "index": 0,
                    "category": "gradeLevel",
                    "status": "Live"
                  },
                  {
                    "identifier": "ekstep_ncert_k-12_subject_mathematics",
                    "code": "mathematics",
                    "translations": null,
                    "name": "Mathematics",
                    "description": "Mathematics",
                    "index": 0,
                    "category": "subject",
                    "status": "Live"
                  },
                  {
                    "identifier": "ekstep_ncert_k-12_gradelevel_class10",
                    "code": "class10",
                    "translations": null,
                    "name": "Class 10",
                    "description": "Class 10",
                    "index": 0,
                    "category": "gradeLevel",
                    "status": "Live"
                  },
                  {
                    "identifier": "ekstep_ncert_k-12_subject_socialscience",
                    "code": "socialscience",
                    "translations": null,
                    "name": "Social Science",
                    "description": "Social Science",
                    "index": 0,
                    "category": "subject",
                    "status": "Live"
                  },
                  {
                    "identifier": "ekstep_ncert_k-12_subject_hindi",
                    "code": "hindi",
                    "translations": null,
                    "name": "Hindi",
                    "description": "Hindi",
                    "index": 0,
                    "category": "subject",
                    "status": "Live"
                  },
                  {
                    "identifier": "ekstep_ncert_k-12_medium_hindi",
                    "code": "hindi",
                    "translations": null,
                    "name": "Hindi",
                    "description": "Hindi",
                    "index": 0,
                    "category": "medium",
                    "status": "Live"
                  },
                  {
                    "identifier": "ekstep_ncert_k-12_subject_economics",
                    "code": "economics",
                    "translations": null,
                    "name": "Economics",
                    "description": "Economics",
                    "index": 0,
                    "category": "subject",
                    "status": "Live"
                  },
                  {
                    "identifier": "ekstep_ncert_k-12_medium_english",
                    "code": "english",
                    "translations": null,
                    "name": "English",
                    "description": "English",
                    "index": 0,
                    "category": "medium",
                    "status": "Live"
                  },
                  {
                    "identifier": "ekstep_ncert_k-12_gradelevel_class3",
                    "code": "class3",
                    "translations": null,
                    "name": "Class 3",
                    "description": "Class 3",
                    "index": 0,
                    "category": "gradeLevel",
                    "status": "Live"
                  },
                  {
                    "identifier": "ekstep_ncert_k-12_subject_environmentalstudies",
                    "code": "environmentalstudies",
                    "translations": null,
                    "name": "Environmental Studies",
                    "description": "Environmental Studies",
                    "index": 0,
                    "category": "subject",
                    "status": "Live"
                  },
                  {
                    "identifier": "ekstep_ncert_k-12_gradelevel_class2",
                    "code": "class2",
                    "translations": null,
                    "name": "Class 2",
                    "description": "Class 2",
                    "index": 0,
                    "category": "gradeLevel",
                    "status": "Live"
                  },
                  {
                    "identifier": "ekstep_ncert_k-12_gradelevel_class9",
                    "code": "class9",
                    "translations": null,
                    "name": "Class 9",
                    "description": "Class 9",
                    "index": 0,
                    "category": "gradeLevel",
                    "status": "Live"
                  },
                  {
                    "identifier": "ekstep_ncert_k-12_subject_healthandphysicaleducation",
                    "code": "healthandphysicaleducation",
                    "translations": null,
                    "name": "Health and Physical Education",
                    "description": "Health and Physical Education",
                    "index": 0,
                    "category": "subject",
                    "status": "Live"
                  },
                  {
                    "identifier": "ekstep_ncert_k-12_subject_history",
                    "code": "history",
                    "translations": null,
                    "name": "History",
                    "description": "History",
                    "index": 0,
                    "category": "subject",
                    "status": "Live"
                  },
                  {
                    "identifier": "ekstep_ncert_k-12_gradelevel_class5",
                    "code": "class5",
                    "translations": null,
                    "name": "Class 5",
                    "description": "Class 5",
                    "index": 0,
                    "category": "gradeLevel",
                    "status": "Live"
                  },
                  {
                    "identifier": "ekstep_ncert_k-12_gradelevel_class8",
                    "code": "class8",
                    "translations": null,
                    "name": "Class 8",
                    "description": "Class 8",
                    "index": 0,
                    "category": "gradeLevel",
                    "status": "Live"
                  },
                  {
                    "identifier": "ekstep_ncert_k-12_gradelevel_class7",
                    "code": "class7",
                    "translations": null,
                    "name": "Class 7",
                    "description": "Class 7",
                    "index": 0,
                    "category": "gradeLevel",
                    "status": "Live"
                  },
                  {
                    "identifier": "ekstep_ncert_k-12_subject_english",
                    "code": "english",
                    "translations": null,
                    "name": "English",
                    "description": "English",
                    "index": 0,
                    "category": "subject",
                    "status": "Live"
                  },
                  {
                    "identifier": "ekstep_ncert_k-12_gradelevel_class6",
                    "code": "class6",
                    "translations": null,
                    "name": "Class 6",
                    "description": "Class 6",
                    "index": 0,
                    "category": "gradeLevel",
                    "status": "Live"
                  },
                  {
                    "identifier": "ekstep_ncert_k-12_subject_politicalsciencecivics",
                    "code": "politicalsciencecivics",
                    "translations": null,
                    "name": "Political Science/Civics",
                    "description": "Political Science/Civics",
                    "index": 0,
                    "category": "subject",
                    "status": "Live"
                  },
                  {
                    "identifier": "ekstep_ncert_k-12_gradelevel_class4",
                    "code": "class4",
                    "translations": null,
                    "name": "Class 4",
                    "description": "Class 4",
                    "index": 0,
                    "category": "gradeLevel",
                    "status": "Live"
                  }
                ],
                "identifier": "ekstep_ncert_k-12_board_cbse",
                "code": "cbse",
                "translations": null,
                "name": "CBSE",
                "description": "CBSE",
                "index": 10,
                "category": "board",
                "status": "Live"
              }
            ],
            "translations": null,
            "name": "Board",
            "description": "Board",
            "index": 1,
            "status": "Live"
          },
          {
            "identifier": "ekstep_ncert_k-12_medium",
            "code": "medium",
            "terms": [
              {
                "associations": [
                  {
                    "identifier": "ekstep_ncert_k-12_gradelevel_class2",
                    "code": "class2",
                    "translations": null,
                    "name": "Class 2",
                    "description": "Class 2",
                    "index": 0,
                    "category": "gradeLevel",
                    "status": "Live"
                  },
                  {
                    "identifier": "ekstep_ncert_k-12_subject_geography",
                    "code": "geography",
                    "translations": null,
                    "name": "Geography",
                    "description": "Geography",
                    "index": 0,
                    "category": "subject",
                    "status": "Live"
                  },
                  {
                    "identifier": "ekstep_ncert_k-12_gradelevel_class10",
                    "code": "class10",
                    "translations": null,
                    "name": "Class 10",
                    "description": "Class 10",
                    "index": 0,
                    "category": "gradeLevel",
                    "status": "Live"
                  },
                  {
                    "identifier": "ekstep_ncert_k-12_subject_hindi",
                    "code": "hindi",
                    "translations": null,
                    "name": "Hindi",
                    "description": "Hindi",
                    "index": 0,
                    "category": "subject",
                    "status": "Live"
                  },
                  {
                    "identifier": "ekstep_ncert_k-12_subject_mathematics",
                    "code": "mathematics",
                    "translations": null,
                    "name": "Mathematics",
                    "description": "Mathematics",
                    "index": 0,
                    "category": "subject",
                    "status": "Live"
                  },
                  {
                    "identifier": "ekstep_ncert_k-12_gradelevel_class1",
                    "code": "class1",
                    "translations": null,
                    "name": "Class 1",
                    "description": "Class 1",
                    "index": 0,
                    "category": "gradeLevel",
                    "status": "Live"
                  },
                  {
                    "identifier": "ekstep_ncert_k-12_subject_economics",
                    "code": "economics",
                    "translations": null,
                    "name": "Economics",
                    "description": "Economics",
                    "index": 0,
                    "category": "subject",
                    "status": "Live"
                  },
                  {
                    "identifier": "ekstep_ncert_k-12_subject_science",
                    "code": "science",
                    "translations": null,
                    "name": "Science",
                    "description": "Science",
                    "index": 0,
                    "category": "subject",
                    "status": "Live"
                  },
                  {
                    "identifier": "ekstep_ncert_k-12_subject_history",
                    "code": "history",
                    "translations": null,
                    "name": "History",
                    "description": "History",
                    "index": 0,
                    "category": "subject",
                    "status": "Live"
                  },
                  {
                    "identifier": "ekstep_ncert_k-12_gradelevel_class9",
                    "code": "class9",
                    "translations": null,
                    "name": "Class 9",
                    "description": "Class 9",
                    "index": 0,
                    "category": "gradeLevel",
                    "status": "Live"
                  },
                  {
                    "identifier": "ekstep_ncert_k-12_subject_healthandphysicaleducation",
                    "code": "healthandphysicaleducation",
                    "translations": null,
                    "name": "Health and Physical Education",
                    "description": "Health and Physical Education",
                    "index": 0,
                    "category": "subject",
                    "status": "Live"
                  },
                  {
                    "identifier": "ekstep_ncert_k-12_gradelevel_class3",
                    "code": "class3",
                    "translations": null,
                    "name": "Class 3",
                    "description": "Class 3",
                    "index": 0,
                    "category": "gradeLevel",
                    "status": "Live"
                  },
                  {
                    "identifier": "ekstep_ncert_k-12_gradelevel_class4",
                    "code": "class4",
                    "translations": null,
                    "name": "Class 4",
                    "description": "Class 4",
                    "index": 0,
                    "category": "gradeLevel",
                    "status": "Live"
                  },
                  {
                    "identifier": "ekstep_ncert_k-12_gradelevel_class5",
                    "code": "class5",
                    "translations": null,
                    "name": "Class 5",
                    "description": "Class 5",
                    "index": 0,
                    "category": "gradeLevel",
                    "status": "Live"
                  },
                  {
                    "identifier": "ekstep_ncert_k-12_subject_environmentalstudies",
                    "code": "environmentalstudies",
                    "translations": null,
                    "name": "Environmental Studies",
                    "description": "Environmental Studies",
                    "index": 0,
                    "category": "subject",
                    "status": "Live"
                  },
                  {
                    "identifier": "ekstep_ncert_k-12_gradelevel_class7",
                    "code": "class7",
                    "translations": null,
                    "name": "Class 7",
                    "description": "Class 7",
                    "index": 0,
                    "category": "gradeLevel",
                    "status": "Live"
                  },
                  {
                    "identifier": "ekstep_ncert_k-12_gradelevel_class6",
                    "code": "class6",
                    "translations": null,
                    "name": "Class 6",
                    "description": "Class 6",
                    "index": 0,
                    "category": "gradeLevel",
                    "status": "Live"
                  },
                  {
                    "identifier": "ekstep_ncert_k-12_subject_socialscience",
                    "code": "socialscience",
                    "translations": null,
                    "name": "Social Science",
                    "description": "Social Science",
                    "index": 0,
                    "category": "subject",
                    "status": "Live"
                  },
                  {
                    "identifier": "ekstep_ncert_k-12_gradelevel_class8",
                    "code": "class8",
                    "translations": null,
                    "name": "Class 8",
                    "description": "Class 8",
                    "index": 0,
                    "category": "gradeLevel",
                    "status": "Live"
                  },
                  {
                    "identifier": "ekstep_ncert_k-12_subject_politicalsciencecivics",
                    "code": "politicalsciencecivics",
                    "translations": null,
                    "name": "Political Science/Civics",
                    "description": "Political Science/Civics",
                    "index": 0,
                    "category": "subject",
                    "status": "Live"
                  },
                  {
                    "identifier": "ekstep_ncert_k-12_subject_english",
                    "code": "english",
                    "translations": null,
                    "name": "English",
                    "description": "English",
                    "index": 0,
                    "category": "subject",
                    "status": "Live"
                  }
                ],
                "identifier": "ekstep_ncert_k-12_medium_english",
                "code": "english",
                "translations": null,
                "name": "English",
                "description": "English",
                "index": 10,
                "category": "medium",
                "status": "Live"
              },
              {
                "associations": [
                  {
                    "identifier": "ekstep_ncert_k-12_gradelevel_class7",
                    "code": "class7",
                    "translations": null,
                    "name": "Class 7",
                    "description": "Class 7",
                    "index": 0,
                    "category": "gradeLevel",
                    "status": "Live"
                  },
                  {
                    "identifier": "ekstep_ncert_k-12_gradelevel_class9",
                    "code": "class9",
                    "translations": null,
                    "name": "Class 9",
                    "description": "Class 9",
                    "index": 0,
                    "category": "gradeLevel",
                    "status": "Live"
                  },
                  {
                    "identifier": "ekstep_ncert_k-12_gradelevel_class6",
                    "code": "class6",
                    "translations": null,
                    "name": "Class 6",
                    "description": "Class 6",
                    "index": 0,
                    "category": "gradeLevel",
                    "status": "Live"
                  },
                  {
                    "identifier": "ekstep_ncert_k-12_gradelevel_class10",
                    "code": "class10",
                    "translations": null,
                    "name": "Class 10",
                    "description": "Class 10",
                    "index": 0,
                    "category": "gradeLevel",
                    "status": "Live"
                  },
                  {
                    "identifier": "ekstep_ncert_k-12_subject_hindi",
                    "code": "hindi",
                    "translations": null,
                    "name": "Hindi",
                    "description": "Hindi",
                    "index": 0,
                    "category": "subject",
                    "status": "Live"
                  },
                  {
                    "identifier": "ekstep_ncert_k-12_gradelevel_class8",
                    "code": "class8",
                    "translations": null,
                    "name": "Class 8",
                    "description": "Class 8",
                    "index": 0,
                    "category": "gradeLevel",
                    "status": "Live"
                  }
                ],
                "identifier": "ekstep_ncert_k-12_medium_hindi",
                "code": "hindi",
                "translations": null,
                "name": "Hindi",
                "description": "Hindi",
                "index": 11,
                "category": "medium",
                "status": "Live"
              }
            ],
            "translations": null,
            "name": "Medium",
            "description": "Medium",
            "index": 2,
            "status": "Live"
          },
          {
            "identifier": "ekstep_ncert_k-12_gradelevel",
            "code": "gradeLevel",
            "terms": [
              {
                "associations": [
                  {
                    "identifier": "ekstep_ncert_k-12_subject_mathematics",
                    "code": "mathematics",
                    "translations": null,
                    "name": "Mathematics",
                    "description": "Mathematics",
                    "index": 0,
                    "category": "subject",
                    "status": "Live"
                  }
                ],
                "identifier": "ekstep_ncert_k-12_gradelevel_class1",
                "code": "class1",
                "translations": null,
                "name": "Class 1",
                "description": "Class 1",
                "index": 1,
                "category": "gradeLevel",
                "status": "Live"
              },
              {
                "associations": [
                  {
                    "identifier": "ekstep_ncert_k-12_subject_mathematics",
                    "code": "mathematics",
                    "translations": null,
                    "name": "Mathematics",
                    "description": "Mathematics",
                    "index": 0,
                    "category": "subject",
                    "status": "Live"
                  }
                ],
                "identifier": "ekstep_ncert_k-12_gradelevel_class2",
                "code": "class2",
                "translations": null,
                "name": "Class 2",
                "description": "Class 2",
                "index": 2,
                "category": "gradeLevel",
                "status": "Live"
              },
              {
                "associations": [
                  {
                    "identifier": "ekstep_ncert_k-12_subject_mathematics",
                    "code": "mathematics",
                    "translations": null,
                    "name": "Mathematics",
                    "description": "Mathematics",
                    "index": 0,
                    "category": "subject",
                    "status": "Live"
                  },
                  {
                    "identifier": "ekstep_ncert_k-12_subject_environmentalstudies",
                    "code": "environmentalstudies",
                    "translations": null,
                    "name": "Environmental Studies",
                    "description": "Environmental Studies",
                    "index": 0,
                    "category": "subject",
                    "status": "Live"
                  }
                ],
                "identifier": "ekstep_ncert_k-12_gradelevel_class3",
                "code": "class3",
                "translations": null,
                "name": "Class 3",
                "description": "Class 3",
                "index": 3,
                "category": "gradeLevel",
                "status": "Live"
              },
              {
                "associations": [
                  {
                    "identifier": "ekstep_ncert_k-12_subject_environmentalstudies",
                    "code": "environmentalstudies",
                    "translations": null,
                    "name": "Environmental Studies",
                    "description": "Environmental Studies",
                    "index": 0,
                    "category": "subject",
                    "status": "Live"
                  },
                  {
                    "identifier": "ekstep_ncert_k-12_subject_mathematics",
                    "code": "mathematics",
                    "translations": null,
                    "name": "Mathematics",
                    "description": "Mathematics",
                    "index": 0,
                    "category": "subject",
                    "status": "Live"
                  }
                ],
                "identifier": "ekstep_ncert_k-12_gradelevel_class4",
                "code": "class4",
                "translations": null,
                "name": "Class 4",
                "description": "Class 4",
                "index": 4,
                "category": "gradeLevel",
                "status": "Live"
              },
              {
                "associations": [
                  {
                    "identifier": "ekstep_ncert_k-12_subject_mathematics",
                    "code": "mathematics",
                    "translations": null,
                    "name": "Mathematics",
                    "description": "Mathematics",
                    "index": 0,
                    "category": "subject",
                    "status": "Live"
                  },
                  {
                    "identifier": "ekstep_ncert_k-12_subject_environmentalstudies",
                    "code": "environmentalstudies",
                    "translations": null,
                    "name": "Environmental Studies",
                    "description": "Environmental Studies",
                    "index": 0,
                    "category": "subject",
                    "status": "Live"
                  }
                ],
                "identifier": "ekstep_ncert_k-12_gradelevel_class5",
                "code": "class5",
                "translations": null,
                "name": "Class 5",
                "description": "Class 5",
                "index": 5,
                "category": "gradeLevel",
                "status": "Live"
              },
              {
                "associations": [
                  {
                    "identifier": "ekstep_ncert_k-12_subject_mathematics",
                    "code": "mathematics",
                    "translations": null,
                    "name": "Mathematics",
                    "description": "Mathematics",
                    "index": 0,
                    "category": "subject",
                    "status": "Live"
                  },
                  {
                    "identifier": "ekstep_ncert_k-12_subject_geography",
                    "code": "geography",
                    "translations": null,
                    "name": "Geography",
                    "description": "Geography",
                    "index": 0,
                    "category": "subject",
                    "status": "Live"
                  },
                  {
                    "identifier": "ekstep_ncert_k-12_subject_hindi",
                    "code": "hindi",
                    "translations": null,
                    "name": "Hindi",
                    "description": "Hindi",
                    "index": 0,
                    "category": "subject",
                    "status": "Live"
                  },
                  {
                    "identifier": "ekstep_ncert_k-12_subject_science",
                    "code": "science",
                    "translations": null,
                    "name": "Science",
                    "description": "Science",
                    "index": 0,
                    "category": "subject",
                    "status": "Live"
                  },
                  {
                    "identifier": "ekstep_ncert_k-12_subject_politicalsciencecivics",
                    "code": "politicalsciencecivics",
                    "translations": null,
                    "name": "Political Science/Civics",
                    "description": "Political Science/Civics",
                    "index": 0,
                    "category": "subject",
                    "status": "Live"
                  },
                  {
                    "identifier": "ekstep_ncert_k-12_subject_history",
                    "code": "history",
                    "translations": null,
                    "name": "History",
                    "description": "History",
                    "index": 0,
                    "category": "subject",
                    "status": "Live"
                  },
                  {
                    "identifier": "ekstep_ncert_k-12_subject_english",
                    "code": "english",
                    "translations": null,
                    "name": "English",
                    "description": "English",
                    "index": 0,
                    "category": "subject",
                    "status": "Live"
                  }
                ],
                "identifier": "ekstep_ncert_k-12_gradelevel_class6",
                "code": "class6",
                "translations": null,
                "name": "Class 6",
                "description": "Class 6",
                "index": 6,
                "category": "gradeLevel",
                "status": "Live"
              },
              {
                "associations": [
                  {
                    "identifier": "ekstep_ncert_k-12_subject_hindi",
                    "code": "hindi",
                    "translations": null,
                    "name": "Hindi",
                    "description": "Hindi",
                    "index": 0,
                    "category": "subject",
                    "status": "Live"
                  },
                  {
                    "identifier": "ekstep_ncert_k-12_subject_science",
                    "code": "science",
                    "translations": null,
                    "name": "Science",
                    "description": "Science",
                    "index": 0,
                    "category": "subject",
                    "status": "Live"
                  },
                  {
                    "identifier": "ekstep_ncert_k-12_subject_geography",
                    "code": "geography",
                    "translations": null,
                    "name": "Geography",
                    "description": "Geography",
                    "index": 0,
                    "category": "subject",
                    "status": "Live"
                  },
                  {
                    "identifier": "ekstep_ncert_k-12_subject_politicalsciencecivics",
                    "code": "politicalsciencecivics",
                    "translations": null,
                    "name": "Political Science/Civics",
                    "description": "Political Science/Civics",
                    "index": 0,
                    "category": "subject",
                    "status": "Live"
                  },
                  {
                    "identifier": "ekstep_ncert_k-12_subject_history",
                    "code": "history",
                    "translations": null,
                    "name": "History",
                    "description": "History",
                    "index": 0,
                    "category": "subject",
                    "status": "Live"
                  },
                  {
                    "identifier": "ekstep_ncert_k-12_subject_mathematics",
                    "code": "mathematics",
                    "translations": null,
                    "name": "Mathematics",
                    "description": "Mathematics",
                    "index": 0,
                    "category": "subject",
                    "status": "Live"
                  },
                  {
                    "identifier": "ekstep_ncert_k-12_subject_english",
                    "code": "english",
                    "translations": null,
                    "name": "English",
                    "description": "English",
                    "index": 0,
                    "category": "subject",
                    "status": "Live"
                  }
                ],
                "identifier": "ekstep_ncert_k-12_gradelevel_class7",
                "code": "class7",
                "translations": null,
                "name": "Class 7",
                "description": "Class 7",
                "index": 7,
                "category": "gradeLevel",
                "status": "Live"
              },
              {
                "associations": [
                  {
                    "identifier": "ekstep_ncert_k-12_subject_science",
                    "code": "science",
                    "translations": null,
                    "name": "Science",
                    "description": "Science",
                    "index": 0,
                    "category": "subject",
                    "status": "Live"
                  },
                  {
                    "identifier": "ekstep_ncert_k-12_subject_history",
                    "code": "history",
                    "translations": null,
                    "name": "History",
                    "description": "History",
                    "index": 0,
                    "category": "subject",
                    "status": "Live"
                  },
                  {
                    "identifier": "ekstep_ncert_k-12_subject_politicalsciencecivics",
                    "code": "politicalsciencecivics",
                    "translations": null,
                    "name": "Political Science/Civics",
                    "description": "Political Science/Civics",
                    "index": 0,
                    "category": "subject",
                    "status": "Live"
                  },
                  {
                    "identifier": "ekstep_ncert_k-12_subject_geography",
                    "code": "geography",
                    "translations": null,
                    "name": "Geography",
                    "description": "Geography",
                    "index": 0,
                    "category": "subject",
                    "status": "Live"
                  },
                  {
                    "identifier": "ekstep_ncert_k-12_subject_hindi",
                    "code": "hindi",
                    "translations": null,
                    "name": "Hindi",
                    "description": "Hindi",
                    "index": 0,
                    "category": "subject",
                    "status": "Live"
                  },
                  {
                    "identifier": "ekstep_ncert_k-12_subject_mathematics",
                    "code": "mathematics",
                    "translations": null,
                    "name": "Mathematics",
                    "description": "Mathematics",
                    "index": 0,
                    "category": "subject",
                    "status": "Live"
                  },
                  {
                    "identifier": "ekstep_ncert_k-12_subject_english",
                    "code": "english",
                    "translations": null,
                    "name": "English",
                    "description": "English",
                    "index": 0,
                    "category": "subject",
                    "status": "Live"
                  }
                ],
                "identifier": "ekstep_ncert_k-12_gradelevel_class8",
                "code": "class8",
                "translations": null,
                "name": "Class 8",
                "description": "Class 8",
                "index": 8,
                "category": "gradeLevel",
                "status": "Live"
              },
              {
                "associations": [
                  {
                    "identifier": "ekstep_ncert_k-12_subject_science",
                    "code": "science",
                    "translations": null,
                    "name": "Science",
                    "description": "Science",
                    "index": 0,
                    "category": "subject",
                    "status": "Live"
                  },
                  {
                    "identifier": "ekstep_ncert_k-12_subject_hindi",
                    "code": "hindi",
                    "translations": null,
                    "name": "Hindi",
                    "description": "Hindi",
                    "index": 0,
                    "category": "subject",
                    "status": "Live"
                  },
                  {
                    "identifier": "ekstep_ncert_k-12_subject_mathematics",
                    "code": "mathematics",
                    "translations": null,
                    "name": "Mathematics",
                    "description": "Mathematics",
                    "index": 0,
                    "category": "subject",
                    "status": "Live"
                  },
                  {
                    "identifier": "ekstep_ncert_k-12_subject_politicalsciencecivics",
                    "code": "politicalsciencecivics",
                    "translations": null,
                    "name": "Political Science/Civics",
                    "description": "Political Science/Civics",
                    "index": 0,
                    "category": "subject",
                    "status": "Live"
                  },
                  {
                    "identifier": "ekstep_ncert_k-12_subject_healthandphysicaleducation",
                    "code": "healthandphysicaleducation",
                    "translations": null,
                    "name": "Health and Physical Education",
                    "description": "Health and Physical Education",
                    "index": 0,
                    "category": "subject",
                    "status": "Live"
                  },
                  {
                    "identifier": "ekstep_ncert_k-12_subject_economics",
                    "code": "economics",
                    "translations": null,
                    "name": "Economics",
                    "description": "Economics",
                    "index": 0,
                    "category": "subject",
                    "status": "Live"
                  },
                  {
                    "identifier": "ekstep_ncert_k-12_subject_geography",
                    "code": "geography",
                    "translations": null,
                    "name": "Geography",
                    "description": "Geography",
                    "index": 0,
                    "category": "subject",
                    "status": "Live"
                  },
                  {
                    "identifier": "ekstep_ncert_k-12_subject_english",
                    "code": "english",
                    "translations": null,
                    "name": "English",
                    "description": "English",
                    "index": 0,
                    "category": "subject",
                    "status": "Live"
                  },
                  {
                    "identifier": "ekstep_ncert_k-12_subject_socialscience",
                    "code": "socialscience",
                    "translations": null,
                    "name": "Social Science",
                    "description": "Social Science",
                    "index": 0,
                    "category": "subject",
                    "status": "Live"
                  },
                  {
                    "identifier": "ekstep_ncert_k-12_subject_history",
                    "code": "history",
                    "translations": null,
                    "name": "History",
                    "description": "History",
                    "index": 0,
                    "category": "subject",
                    "status": "Live"
                  }
                ],
                "identifier": "ekstep_ncert_k-12_gradelevel_class9",
                "code": "class9",
                "translations": null,
                "name": "Class 9",
                "description": "Class 9",
                "index": 9,
                "category": "gradeLevel",
                "status": "Live"
              },
              {
                "associations": [
                  {
                    "identifier": "ekstep_ncert_k-12_subject_english",
                    "code": "english",
                    "translations": null,
                    "name": "English",
                    "description": "English",
                    "index": 0,
                    "category": "subject",
                    "status": "Live"
                  },
                  {
                    "identifier": "ekstep_ncert_k-12_subject_history",
                    "code": "history",
                    "translations": null,
                    "name": "History",
                    "description": "History",
                    "index": 0,
                    "category": "subject",
                    "status": "Live"
                  },
                  {
                    "identifier": "ekstep_ncert_k-12_subject_hindi",
                    "code": "hindi",
                    "translations": null,
                    "name": "Hindi",
                    "description": "Hindi",
                    "index": 0,
                    "category": "subject",
                    "status": "Live"
                  },
                  {
                    "identifier": "ekstep_ncert_k-12_subject_science",
                    "code": "science",
                    "translations": null,
                    "name": "Science",
                    "description": "Science",
                    "index": 0,
                    "category": "subject",
                    "status": "Live"
                  },
                  {
                    "identifier": "ekstep_ncert_k-12_subject_mathematics",
                    "code": "mathematics",
                    "translations": null,
                    "name": "Mathematics",
                    "description": "Mathematics",
                    "index": 0,
                    "category": "subject",
                    "status": "Live"
                  },
                  {
                    "identifier": "ekstep_ncert_k-12_subject_geography",
                    "code": "geography",
                    "translations": null,
                    "name": "Geography",
                    "description": "Geography",
                    "index": 0,
                    "category": "subject",
                    "status": "Live"
                  },
                  {
                    "identifier": "ekstep_ncert_k-12_subject_politicalsciencecivics",
                    "code": "politicalsciencecivics",
                    "translations": null,
                    "name": "Political Science/Civics",
                    "description": "Political Science/Civics",
                    "index": 0,
                    "category": "subject",
                    "status": "Live"
                  },
                  {
                    "identifier": "ekstep_ncert_k-12_subject_socialscience",
                    "code": "socialscience",
                    "translations": null,
                    "name": "Social Science",
                    "description": "Social Science",
                    "index": 0,
                    "category": "subject",
                    "status": "Live"
                  },
                  {
                    "identifier": "ekstep_ncert_k-12_subject_economics",
                    "code": "economics",
                    "translations": null,
                    "name": "Economics",
                    "description": "Economics",
                    "index": 0,
                    "category": "subject",
                    "status": "Live"
                  }
                ],
                "identifier": "ekstep_ncert_k-12_gradelevel_class10",
                "code": "class10",
                "translations": null,
                "name": "Class 10",
                "description": "Class 10",
                "index": 10,
                "category": "gradeLevel",
                "status": "Live"
              }
            ],
            "translations": null,
            "name": "Grade",
            "description": "Grade",
            "index": 3,
            "status": "Live"
          },
          {
            "identifier": "ekstep_ncert_k-12_subject",
            "code": "subject",
            "terms": [
              {
                "identifier": "ekstep_ncert_k-12_subject_environmentalstudies",
                "code": "environmentalstudies",
                "translations": null,
                "name": "Environmental Studies",
                "description": "Environmental Studies",
                "index": 10,
                "category": "subject",
                "status": "Live"
              },
              {
                "identifier": "ekstep_ncert_k-12_subject_geography",
                "code": "geography",
                "translations": null,
                "name": "Geography",
                "description": "Geography",
                "index": 11,
                "category": "subject",
                "status": "Live"
              },
              {
                "identifier": "ekstep_ncert_k-12_subject_healthandphysicaleducation",
                "code": "healthandphysicaleducation",
                "translations": null,
                "name": "Health and Physical Education",
                "description": "Health and Physical Education",
                "index": 11,
                "category": "subject",
                "status": "Live"
              },
              {
                "identifier": "ekstep_ncert_k-12_subject_socialscience",
                "code": "socialscience",
                "translations": null,
                "name": "Social Science",
                "description": "Social Science",
                "index": 12,
                "category": "subject",
                "status": "Live"
              },
              {
                "identifier": "ekstep_ncert_k-12_subject_politicalsciencecivics",
                "code": "politicalsciencecivics",
                "translations": null,
                "name": "Political Science/Civics",
                "description": "Political Science/Civics",
                "index": 12,
                "category": "subject",
                "status": "Live"
              },
              {
                "identifier": "ekstep_ncert_k-12_subject_mathematics",
                "code": "mathematics",
                "translations": null,
                "name": "Mathematics",
                "description": "Mathematics",
                "index": 15,
                "category": "subject",
                "status": "Live"
              },
              {
                "identifier": "ekstep_ncert_k-12_subject_history",
                "code": "history",
                "translations": null,
                "name": "History",
                "description": "History",
                "index": 16,
                "category": "subject",
                "status": "Live"
              },
              {
                "identifier": "ekstep_ncert_k-12_subject_science",
                "code": "science",
                "translations": null,
                "name": "Science",
                "description": "Science",
                "index": 17,
                "category": "subject",
                "status": "Live"
              },
              {
                "identifier": "ekstep_ncert_k-12_subject_hindi",
                "code": "hindi",
                "translations": null,
                "name": "Hindi",
                "description": "Hindi",
                "index": 18,
                "category": "subject",
                "status": "Live"
              },
              {
                "identifier": "ekstep_ncert_k-12_subject_english",
                "code": "english",
                "translations": null,
                "name": "English",
                "description": "English",
                "index": 19,
                "category": "subject",
                "status": "Live"
              },
              {
                "identifier": "ekstep_ncert_k-12_subject_economics",
                "code": "economics",
                "translations": null,
                "name": "Economics",
                "description": "Economics",
                "index": 20,
                "category": "subject",
                "status": "Live"
              }
            ],
            "translations": null,
            "name": "Subject",
            "description": "Subject",
            "index": 4,
            "status": "Live"
          }
        ],
        "type": "K-12",
        "objectType": "Framework"
      }
    }
  }